snakemake_logger_plugin_sqlite/__init__.py
snakemake_logger_plugin_sqlite/event_handlers.py
snakemake_logger_plugin_sqlite/log_handler.py
snakemake_logger_plugin_sqlite/parsers.py
snakemake_logger_plugin_sqlite/py.typed
snakemake_logger_plugin_sqlite/db/__init__.py
snakemake_logger_plugin_sqlite/db/session.py
snakemake_logger_plugin_sqlite/models/__init__.py
snakemake_logger_plugin_sqlite/models/base.py
snakemake_logger_plugin_sqlite/models/enums.py
snakemake_logger_plugin_sqlite/models/error.py
snakemake_logger_plugin_sqlite/models/file.py
snakemake_logger_plugin_sqlite/models/job.py
snakemake_logger_plugin_sqlite/models/rule.py
snakemake_logger_plugin_sqlite/models/workflow.py
snakemake_logger_plugin_sqlite-0.1.1.dist-info/METADATA
snakemake_logger_plugin_sqlite-0.1.1.dist-info/WHEEL
snakemake_logger_plugin_sqlite-0.1.1.dist-info/licenses/LICENSE
snakemake_logger_plugin_sqlite-0.1.1.dist-info/RECORD
