Metadata-Version: 2.4
Name: snakemake-logger-plugin-sqlite
Version: 0.1.1
Summary: Snakemake logger plugin that writes logs to SQLite database.
Author-email: Cade Mirchandani <cmirchan@ucsc.edu>
License-File: LICENSE
Requires-Python: <4.0,>=3.11
Requires-Dist: snakemake-interface-logger-plugins>=1.2.0
Requires-Dist: sqlalchemy>=2.0.38
Provides-Extra: dev
Requires-Dist: loguru>=0.7.3; extra == 'dev'
Requires-Dist: pytest>=8.3.5; extra == 'dev'
Requires-Dist: ruff>=0.9.10; extra == 'dev'
Requires-Dist: snakemake>=9.0.1; extra == 'dev'
